MANIFEST.in
README.md
setup.py
mrpython/__init__.py
mrpython/data.py
mrpython/fxn.py
mrpython.egg-info/PKG-INFO
mrpython.egg-info/SOURCES.txt
mrpython.egg-info/dependency_links.txt
mrpython.egg-info/requires.txt
mrpython.egg-info/top_level.txt
mrpython/tests/__init__.py
mrpython/tests/test_data.py
mrpython/tests/test_fxn.py