Metadata-Version: 1.1
Name: mrpython
Version: 0.0.10
Summary: Collection of things for Python that dont warrant their own libraries.
Home-page: http://github.com/petermelias/mrpython
Author: Peter M. Elias
Author-email: petermelias@gmail.com
License: MIT
Platform: UNKNOWN
Classifier: Environment :: Web Environment
Classifier: Intended Audience :: Developers
Classifier: License :: OSI Approved :: MIT License
Classifier: Operating System :: OS Independent
Classifier: Programming Language :: Python
Classifier: Topic :: Internet :: WWW/HTTP :: Dynamic Content
Classifier: Topic :: Software Development :: Libraries :: Python Modules
